resume_parser/__init__.py
resume_parser/openai_api.py
resume_parser_ai-0.0.1.dist-info/LICENSE
resume_parser_ai-0.0.1.dist-info/METADATA
resume_parser_ai-0.0.1.dist-info/WHEEL
resume_parser_ai-0.0.1.dist-info/entry_points.txt
resume_parser_ai-0.0.1.dist-info/top_level.txt
resume_parser_ai-0.0.1.dist-info/RECORD
