Metadata-Version: 2.1
Name: resume-parser-ai
Version: 0.0.1
Summary: A package to parse resumes and extract structured data using OpenAI API
Home-page: https://github.com/resumeupai/resume-parser-ai
Author: ResumeUp.AI
Author-email: accounts@resumeup.ai
License: UNKNOWN
Platform: UNKNOWN
Classifier: Programming Language :: Python :: 3
Classifier: License :: OSI Approved :: MIT License
Classifier: Operating System :: OS Independent
Requires-Python: >=3.6
Requires-Dist: pdfplumber
Requires-Dist: python-docx
Requires-Dist: openai
